mocodo/__init__.py
mocodo/__main__.py
mocodo/api.py
mocodo/argument_parser.py
mocodo/association.py
mocodo/attribute.py
mocodo/common.py
mocodo/constraint.py
mocodo/diagram_link.py
mocodo/entity.py
mocodo/font_metrics.py
mocodo/grid.py
mocodo/guess_title.py
mocodo/inheritance.py
mocodo/leg.py
mocodo/magic.py
mocodo/mcd.py
mocodo/mcd_to_svg.py
mocodo/mocodo_error.py
mocodo/parse_mcd.py
mocodo/phantom.py
mocodo/convert/__init__.py
mocodo/convert/_ast.py
mocodo/convert/_chen.py
mocodo/convert/_crow.py
mocodo/convert/_data_dict.py
mocodo/convert/_prompt.py
mocodo/convert/_share.py
mocodo/convert/_uml.py
mocodo/convert/crow_gv.py
mocodo/convert/crow_mmd.py
mocodo/convert/read_template.py
mocodo/convert/relations.py
mocodo/dev/json_to_yaml_templates.py
mocodo/dev/update_sql_reserved_words.py
mocodo/dev/update_transfo_metadata.py
mocodo/resources/default_datatypes_en.tsv
mocodo/resources/default_datatypes_fr.tsv
mocodo/resources/font_metrics.json
mocodo/resources/grammar.lark
mocodo/resources/pristine_sandbox.mcd
mocodo/resources/rendering_services.json
mocodo/resources/transformations.json
mocodo/resources/colors/blank.json
mocodo/resources/colors/brewer+1.json
mocodo/resources/colors/brewer+2.json
mocodo/resources/colors/brewer+3.json
mocodo/resources/colors/brewer+4.json
mocodo/resources/colors/brewer+5.json
mocodo/resources/colors/brewer+6.json
mocodo/resources/colors/brewer+7.json
mocodo/resources/colors/brewer+8.json
mocodo/resources/colors/brewer+9.json
mocodo/resources/colors/brewer-1.json
mocodo/resources/colors/brewer-2.json
mocodo/resources/colors/brewer-3.json
mocodo/resources/colors/brewer-4.json
mocodo/resources/colors/brewer-5.json
mocodo/resources/colors/brewer-6.json
mocodo/resources/colors/brewer-7.json
mocodo/resources/colors/brewer-8.json
mocodo/resources/colors/brewer-9.json
mocodo/resources/colors/bw-alpha.json
mocodo/resources/colors/bw.json
mocodo/resources/colors/dark-desert.json
mocodo/resources/colors/dark-ocean.json
mocodo-4.3.3.dist-info/METADATA
mocodo-4.3.3.dist-info/WHEEL
mocodo-4.3.3.dist-info/entry_points.txt
mocodo-4.3.3.dist-info/licenses/LICENSE
mocodo-4.3.3.dist-info/RECORD
