Metadata-Version: 2.4
Name: mocodo
Version: 4.3.3
Summary: Modélisation Conceptuelle de Données. Nickel. Ni souris.
Project-URL: Homepage, https://www.mocodo.net/
Project-URL: Repository, https://github.com/laowantong/mocodo/
Project-URL: issues, https://github.com/laowantong/mocodo/issues
Author: Aristide Grange
License-Expression: MIT
License-File: LICENSE
Keywords: ERD,Merise,SVG,database,drawing,education,relational
Classifier: Development Status :: 5 - Production/Stable
Classifier: Environment :: Console
Classifier: Framework :: IPython
Classifier: Intended Audience :: Education
Classifier: Intended Audience :: Information Technology
Classifier: License :: OSI Approved :: MIT License
Classifier: Natural Language :: English
Classifier: Operating System :: OS Independent
Classifier: Programming Language :: Python :: 3
Classifier: Programming Language :: Python :: 3.6
Classifier: Topic :: Database
Classifier: Topic :: Education
Requires-Python: <4,>=3.6.1
Requires-Dist: requests<3,>=2.22.0
Provides-Extra: clipboard
Requires-Dist: pyperclip>=1.9.0; extra == 'clipboard'
Provides-Extra: svg
Requires-Dist: cairosvg>=2.7.1; extra == 'svg'
